Metadata-Version: 2.1
Name: httpie-oauth2-client-credentials
Version: 0.2.0
Summary: httpie auth plugin for OAuth2.0 client credentials flow.
Home-page: https://github.com/satodoc/httpie-oauth2-client-credentials
Download-URL: https://github.com/satodoc/httpie-oauth2-client-credentials
Author: satdoc
Author-email: satodoc-develop-public@outlook.com
License: MIT
Classifier: Development Status :: 4 - Beta
Classifier: Programming Language :: Python
Classifier: Intended Audience :: Developers
Classifier: Environment :: Console
Classifier: Environment :: Plugins
Classifier: License :: OSI Approved :: MIT License
Classifier: Topic :: Internet :: WWW/HTTP
Classifier: Topic :: Utilities
License-File: LICENSE
Requires-Dist: httpie (>=3.2.2)
